telegram_sleuth/__init__.py
telegram_sleuth-0.0.1.post7.dist-info/licenses/LICENSE
telegram_sleuth-0.0.1.post7.dist-info/METADATA
telegram_sleuth-0.0.1.post7.dist-info/WHEEL
telegram_sleuth-0.0.1.post7.dist-info/top_level.txt
telegram_sleuth-0.0.1.post7.dist-info/RECORD
