Metadata-Version: 2.4
Name: telegram_sleuth
Version: 0.0.1.post7
Summary: Extract and analyze data from Telegram group chats
Author-email: M Naufal Hanif <naufalmng@gmail.com>
Project-URL: Homepage, https://github.com/naufalmng/telegram-group-sleuth
Project-URL: Issues, https://github.com/naufalmng/telegram-group-sleuth/issues
Classifier: Programming Language :: Python :: 3
Classifier: License :: OSI Approved :: GNU General Public License v3 (GPLv3)
Classifier: Operating System :: OS Independent
Requires-Python: >=3.6
License-File: LICENSE
Dynamic: license-file
